openfasoc/__init__.py
openfasoc/config.py
openfasoc/generators/__init__.py
openfasoc/generators/common/__init__.py
openfasoc/generators/common/check_gen_files.py
openfasoc/generators/common/get_ngspice_version.py
openfasoc/generators/common/verilog_generation.py
openfasoc/generators/common/simulation/__init__.py
openfasoc/generators/common/simulation/classify_sim_error.py
openfasoc/generators/common/simulation/simulation_config.py
openfasoc/generators/common/simulation/simulation_run.py
openfasoc/generators/common/simulation/utils.py
openfasoc/generators/gdsfactory_gen/__init__.py
openfasoc/generators/gdsfactory_gen/process_input.py
openfasoc/generators/gdsfactory_gen/relational.py
openfasoc/generators/gdsfactory_gen/run.py
openfasoc/generators/gdsfactory_gen/glayout/__init__.py
openfasoc/generators/gdsfactory_gen/glayout/components/__init__.py
openfasoc/generators/gdsfactory_gen/glayout/components/diff_pair.py
openfasoc/generators/gdsfactory_gen/glayout/components/diff_pair_cmirrorbias.py
openfasoc/generators/gdsfactory_gen/glayout/components/diff_pair_stackedcmirror.py
openfasoc/generators/gdsfactory_gen/glayout/components/differential_to_single_ended_converter.py
openfasoc/generators/gdsfactory_gen/glayout/components/opamp.py
openfasoc/generators/gdsfactory_gen/glayout/components/opamp_twostage.py
openfasoc/generators/gdsfactory_gen/glayout/components/row_csamplifier_diff_to_single_ended_converter.py
openfasoc/generators/gdsfactory_gen/glayout/components/stacked_current_mirror.py
openfasoc/generators/gdsfactory_gen/glayout/pdk/__init__.py
openfasoc/generators/gdsfactory_gen/glayout/pdk/mappedpdk.py
openfasoc/generators/gdsfactory_gen/glayout/pdk/gf180_mapped/__init__.py
openfasoc/generators/gdsfactory_gen/glayout/pdk/gf180_mapped/gf180_mapped.py
openfasoc/generators/gdsfactory_gen/glayout/pdk/gf180_mapped/grules.py
openfasoc/generators/gdsfactory_gen/glayout/pdk/sky130_mapped/__init__.py
openfasoc/generators/gdsfactory_gen/glayout/pdk/sky130_mapped/grules.py
OpenFASoC-0.0.4.dist-info/LICENSE
OpenFASoC-0.0.4.dist-info/METADATA
OpenFASoC-0.0.4.dist-info/WHEEL
OpenFASoC-0.0.4.dist-info/top_level.txt
OpenFASoC-0.0.4.dist-info/RECORD
