Metadata-Version: 2.1
Name: OpenFASoC
Version: 0.0.4
Summary: Fully Open-Source Autonomous SoC Synthesis using Customizable Cell-Based Synthesizable Analog Circuits
Home-page: https://github.com/idea-fasoc/OpenFASOC
Author: msaligane
Author-email: mehdi@umich.edu
License: MIT
Classifier: Development Status :: 2 - Pre-Alpha
Classifier: License :: OSI Approved :: MIT License
Classifier: Programming Language :: Python
Classifier: Programming Language :: Python :: 3.10
Requires-Python: >=3.10
License-File: LICENSE
Requires-Dist: pandas
Requires-Dist: klayout
Requires-Dist: numpy
Requires-Dist: matplotlib
Requires-Dist: gdsfactory ==7.7.0
Requires-Dist: nbsphinx
Requires-Dist: cairosvg
Requires-Dist: scipy
Requires-Dist: ltspice
Requires-Dist: mako
Requires-Dist: prettyprinttree
Requires-Dist: scikit-learn
Requires-Dist: seaborn
